opi/__init__.py
opi/core.py
opi/execution/__init__.py
opi/execution/core.py
opi/input/__init__.py
opi/input/arbitrary_string.py
opi/input/core.py
opi/input/blocks/__init__.py
opi/input/blocks/base.py
opi/input/blocks/block_autoci.py
opi/input/blocks/block_basis.py
opi/input/blocks/block_casscf.py
opi/input/blocks/block_cis.py
opi/input/blocks/block_cosmors.py
opi/input/blocks/block_cpcm.py
opi/input/blocks/block_docker.py
opi/input/blocks/block_eda.py
opi/input/blocks/block_elprop.py
opi/input/blocks/block_eprnmr.py
opi/input/blocks/block_frag.py
opi/input/blocks/block_freq.py
opi/input/blocks/block_geom.py
opi/input/blocks/block_goat.py
opi/input/blocks/block_ice.py
opi/input/blocks/block_irc.py
opi/input/blocks/block_loc.py
opi/input/blocks/block_mdci.py
opi/input/blocks/block_method.py
opi/input/blocks/block_mp2.py
opi/input/blocks/block_neb.py
opi/input/blocks/block_output.py
opi/input/blocks/block_qmmm.py
opi/input/blocks/block_rel.py
opi/input/blocks/block_rocis.py
opi/input/blocks/block_scf.py
opi/input/blocks/block_solvator.py
opi/input/blocks/block_tddft.py
opi/input/blocks/block_xtb.py
opi/input/blocks/fragment.py
opi/input/blocks/geom_wrapper.py
opi/input/simple_keywords/__init__.py
opi/input/simple_keywords/approximation.py
opi/input/simple_keywords/atomic_charge.py
opi/input/simple_keywords/aux_basis_set.py
opi/input/simple_keywords/avas.py
opi/input/simple_keywords/base.py
opi/input/simple_keywords/basis_set.py
opi/input/simple_keywords/basisoption.py
opi/input/simple_keywords/dft.py
opi/input/simple_keywords/dispersion_correction.py
opi/input/simple_keywords/dlpno.py
opi/input/simple_keywords/docker.py
opi/input/simple_keywords/ecp.py
opi/input/simple_keywords/esd.py
opi/input/simple_keywords/force_field.py
opi/input/simple_keywords/gcp.py
opi/input/simple_keywords/goat.py
opi/input/simple_keywords/grid.py
opi/input/simple_keywords/method.py
opi/input/simple_keywords/miscellaneous.py
opi/input/simple_keywords/neb.py
opi/input/simple_keywords/opt.py
orca_pi-1.0.1.dist-info/METADATA
orca_pi-1.0.1.dist-info/WHEEL
orca_pi-1.0.1.dist-info/licenses/LICENSE
orca_pi-1.0.1.dist-info/RECORD
