Metadata-Version: 2.4
Name: orca-pi
Version: 1.0.1
Summary: Python interface for the quantum chemical ORCA software package.
Project-URL: Homepage, https://faccts.de
Project-URL: Documentation, https://www.faccts.de/docs/opi/nightly/docs/
Project-URL: Repository, https://github.com/faccts/opi
Project-URL: Issues, https://github.com/faccts/opi/issues
Project-URL: Changelog, https://github.com/faccts/opi/blob/main/CHANGELOG.md
Author-email: FACCTS GmbH <info@faccts.de>
License: This open source project is licensed under GPL-3.0. 
License-File: LICENSE
Keywords: chemistry,hpc,interface,machine learning,orca
Classifier: Development Status :: 5 - Production/Stable
Classifier: Intended Audience :: Developers
Classifier: License :: Other/Proprietary License
Classifier: Operating System :: OS Independent
Classifier: Programming Language :: Python :: 3
Requires-Python: >=3.11
Requires-Dist: numpy<3,>=2.2.6
Requires-Dist: platformdirs<5,>=4.3.8
Requires-Dist: pydantic<3,>=2.11.5
Requires-Dist: rdkit<2026,>=2025.3.2
Requires-Dist: semantic-version<3,>=2.10.0
